narrate_gpt/__init__.py
narrate_gpt/cli.py
narrate_gpt/openai.py
narrate_gpt-0.1.0.dist-info/licenses/LICENSE
narrate_gpt-0.1.0.dist-info/METADATA
narrate_gpt-0.1.0.dist-info/WHEEL
narrate_gpt-0.1.0.dist-info/entry_points.txt
narrate_gpt-0.1.0.dist-info/top_level.txt
narrate_gpt-0.1.0.dist-info/RECORD
