Metadata-Version: 2.4
Name: narrate-gpt
Version: 0.1.0
Summary: narrate-gpt
Author-email: Frank Odom <frank.odom.iii@gmail.com>
License: MIT
Classifier: Programming Language :: Python :: 3
Requires-Python: >=3.11
License-File: LICENSE
Requires-Dist: openai[voice-helpers]<2.0.0,>=1.75.0
Requires-Dist: pyperclip<2.0.0,>=1.9.0
Provides-Extra: test
Requires-Dist: black; extra == "test"
Requires-Dist: mypy; extra == "test"
Requires-Dist: pre-commit; extra == "test"
Requires-Dist: pytest; extra == "test"
Requires-Dist: pytest-cov; extra == "test"
Requires-Dist: ruff; extra == "test"
Dynamic: license-file
